[
  {
    "id": 1,
    "title": "camisa rallada",
    "price": 1000,
    "description": "Es una remera buenísima",
    "category": "camisas",
    "colors": ["white", "black", "blue"],
    "images": ["../img/products/camisas/camisa1/1.png"],
    "stock": 5
  },
  {
    "id": 2,
    "title": "camisa lisa",
    "price": 1000,
    "description": "Es una remera buenísima",
    "category": "camisas",
    "colors": ["white", "black", "blue"],
    "images": ["../img/products/camisas/camisa2/1.jpg"],
    "stock": 5
  },
  {
    "id": 3,
    "title": "camisa a cuadros",
    "price": 1000,
    "description": "Es una remera buenísima",
    "category": "camisas",
    "colors": ["white", "black", "blue"],
    "images": ["../img/products/camisas/camisa3/1.png"],
    "stock": 5
  },
  {
    "id": 4,
    "title": "camisa slim fit",
    "price": 1000,
    "description": "Es una remera buenísima",
    "category": "camisas",
    "colors": ["gris", "negro", "blue"],
    "images": [
      "../img/products/camisas/camisa4/1.jpg",
      "../img/products/camisas/camisa4/2.jpg",
      "../img/products/camisas/camisa4/3.jpg"
    ],
    "stock": 5
  },
  {
    "id": 5,
    "title": "camisa suelta",
    "price": 1000,
    "description": "Es una remera buenísima",
    "category": "camisas",
    "colors": ["gris", "negro", "blue"],
    "images": ["../img/products/camisas/camisa5/1.jpg"],
    "stock": 5
  },
  {
    "id": 6,
    "title": "pantalon slim fit",
    "price": 1000,
    "description": "Es una remera buenísima",
    "category": "pantalones",
    "colors": ["gris", "negro", "blue"],
    "images": [
      "../img/products/pantalones/pantalon1/1.jpg",
      "../img/products/pantalones/pantalon1/2.jpg"
    ],
    "stock": 5
  },
  {
    "id": 7,
    "title": "pantalon trabajo",
    "price": 1000,
    "description": "Es una remera buenísima",
    "category": "pantalones",
    "colors": ["gris", "negro", "blue"],
    "images": ["../img/products/pantalones/pantalon2/1.jpg"],
    "stock": 5
  },
  {
    "id": 8,
    "title": "pantalon salir",
    "price": 1000,
    "description": "Es una remera buenísima",
    "category": "pantalones",
    "colors": ["gris", "negro", "blue"],
    "images": [
      "../img/products/pantalones/pantalon3/1.jpg",
      "../img/products/pantalones/pantalon3/2.jpg"
    ],
    "stock": 5
  },
  {
    "id": 9,
    "title": "pantalon",
    "price": 1000,
    "description": "Es una remera buenísima",
    "category": "pantalones",
    "colors": ["gris", "negro", "blue"],
    "images": [
      "../img/products/pantalones/pantalon4/1.jpg",
      "../img/products/pantalones/pantalon4/2.jpg"
    ],
    "stock": 5
  },
  {
    "id": 10,
    "title": "reloj 1",
    "price": 1000,
    "description": "Es una remera buenísima",
    "category": "relojes",
    "colors": ["gris", "negro", "blue"],
    "images": ["../img/products/relojes/reloj1/1.jpg"],
    "stock": 5
  },
  {
    "id": 11,
    "title": "reloj 2",
    "price": 1000,
    "description": "Es una remera buenísima",
    "category": "relojes",
    "colors": ["gris", "negro", "blue"],
    "images": ["../img/products/relojes/reloj2/1.jpg"],
    "stock": 5
  },
  {
    "id": 12,
    "title": "reloj 3",
    "price": 1000,
    "description": "Es una remera buenísima",
    "category": "relojes",
    "colors": ["gris", "negro", "blue"],
    "images": ["../img/products/relojes/reloj3/1.jpg"],
    "stock": 5
  },
  {
    "id": 13,
    "title": "reloj 4",
    "price": 1000,
    "description": "Es una remera buenísima",
    "category": "relojes",
    "colors": ["gris", "negro", "blue"],
    "images": ["../img/products/relojes/reloj4/1.jpg"],
    "stock": 5
  },
  {
    "id": 14,
    "title": "reloj 5",
    "price": 1000,
    "description": "Es una remera buenísima",
    "category": "relojes",
    "colors": ["gris", "negro", "blue"],
    "images": ["../img/products/relojes/reloj5/1.jpg"],
    "stock": 5
  },
  {
    "id": 15,
    "title": "reloj 6",
    "price": 1000,
    "description": "Es una remera buenísima",
    "category": "relojes",
    "colors": ["gris", "negro", "blue"],
    "images": ["../img/products/relojes/reloj6/1.jpg"],
    "stock": 5
  },
  {
    "id": 16,
    "title": "saco fachero",
    "price": 1000,
    "description": "Es una remera buenísima",
    "category": "sacos",
    "colors": ["gris", "negro", "blue"],
    "images": ["../img/products/sacos/saco1/1.jpg"],
    "stock": 5
  },
  {
    "id": 17,
    "title": "saco 2",
    "price": 1000,
    "description": "Es una remera buenísima",
    "category": "sacos",
    "colors": ["gris", "negro", "blue"],
    "images": [
      "../img/products/sacos/saco2/1.jpg",
      "../img/products/sacos/saco2/2.jpg"
    ],
    "stock": 5
  },
  {
    "id": 18,
    "title": "saco 3",
    "price": 1000,
    "description": "Es una remera buenísima",
    "category": "sacos",
    "colors": ["gris", "negro", "blue"],
    "images": [
      "../img/products/sacos/saco3/1.jpg",
      "../img/products/sacos/saco3/2.jpg"
    ],
    "stock": 5
  },
  {
    "id": 19,
    "title": "saco 4",
    "price": 1000,
    "description": "Es una remera buenísima",
    "category": "sacos",
    "colors": ["gris", "negro", "blue"],
    "images": ["../img/products/sacos/saco4/1.jpg"],
    "stock": 5
  },
  {
    "id": 20,
    "title": "zapato 1",
    "price": 1000,
    "description": "Es una remera buenísima",
    "category": "zapatos",
    "colors": ["gris", "negro", "blue"],
    "images": [
      "../img/products/zapatos/zapato1/1.jpg",
      "../img/products/zapatos/zapato1/2.jpg",
      "../img/products/zapatos/zapato1/3.jpg"
    ],
    "stock": 5
  },
  {
    "id": 21,
    "title": "zapato 2",
    "price": 1000,
    "description": "Es una remera buenísima",
    "category": "zapatos",
    "colors": ["gris", "negro", "blue"],
    "images": ["../img/products/zapatos/zapato2/1.jpg"],
    "stock": 5
  },
  {
    "id": 22,
    "title": "zapato 3",
    "price": 1000,
    "description": "Es una remera buenísima",
    "category": "zapatos",
    "colors": ["gris", "negro", "blue"],
    "images": ["../img/products/zapatos/zapato3/1.jpg"],
    "stock": 5
  },
  {
    "id": 23,
    "title": "zapato 4",
    "price": 1000,
    "description": "Es una remera buenísima",
    "category": "zapatos",
    "colors": ["gris", "negro", "blue"],
    "images": ["../img/products/zapatos/zapato4/1.jpg"],
    "stock": 5
  }
]
